redlock-1.1.0.dist-info/metadata.json
redlock-1.1.0.dist-info/METADATA
redlock-1.1.0.dist-info/top_level.txt
redlock-1.1.0.dist-info/RECORD
redlock-1.1.0.dist-info/DESCRIPTION.rst
redlock-1.1.0.dist-info/WHEEL
redlock/__init__.py
redlock/lock.py
