Metadata-Version: 2.0
Name: redlock
Version: 1.1.0
Summary: Distributed locks with Redis
Home-page: https://github.com/glasslion/redlock
Author: Leonardo Zhou
Author-email: glasslion@gmail.com
License: MIT
Keywords: redis lock distributed
Platform: UNKNOWN
Classifier: Development Status :: 5 - Production/Stable
Classifier: Intended Audience :: Developers
Classifier: License :: OSI Approved :: MIT License
Classifier: Programming Language :: Python :: 2
Classifier: Programming Language :: Python :: 2.6
Classifier: Programming Language :: Python :: 2.7
Classifier: Programming Language :: Python :: 3
Classifier: Programming Language :: Python :: 3.2
Classifier: Programming Language :: Python :: 3.3
Classifier: Programming Language :: Python :: 3.4
Requires-Dist: redis
